pykaal/__init__.py
pykaal/_io.py
pykaal/_picoharp_300.py
pykaal/_picoharp_parser.py
pykaal-0.0.2.dist-info/LICENSE.txt
pykaal-0.0.2.dist-info/WHEEL
pykaal-0.0.2.dist-info/METADATA
pykaal-0.0.2.dist-info/RECORD
