Metadata-Version: 2.1
Name: pykaal
Version: 0.0.2
Summary: Fluorescence time analysis
License: MIT
Author: Sarthak Jariwala
Author-email: jariwala@uw.edu
Requires-Python: >=3.6,<4.0
Classifier: License :: OSI Approved :: MIT License
Classifier: Programming Language :: Python :: 3
Classifier: Programming Language :: Python :: 3.6
Classifier: Programming Language :: Python :: 3.7
Classifier: Programming Language :: Python :: 3.8
Classifier: Programming Language :: Python :: 3.9
Requires-Dist: importlib_metadata (>=1.7.0,<2.0.0); python_version < "3.8"
Requires-Dist: matplotlib (==3.3.0)
Requires-Dist: numpy (==1.19.1)
